zope/schema/__init__.py
zope/schema/_bootstrapfields.py
zope/schema/_bootstrapinterfaces.py
zope/schema/_field.py
zope/schema/_messageid.py
zope/schema/_schema.py
zope/schema/accessors.py
zope/schema/fieldproperty.py
zope/schema/interfaces.py
zope/schema/vocabulary.py
zope/schema/tests/__init__.py
zope/schema/tests/states.py
zope/schema/tests/test__bootstrapfields.py
zope/schema/tests/test__bootstrapinterfaces.py
zope/schema/tests/test__field.py
zope/schema/tests/test__messageid.py
zope/schema/tests/test_accessors.py
zope/schema/tests/test_equality.py
zope/schema/tests/test_fieldproperty.py
zope/schema/tests/test_interfaces.py
zope/schema/tests/test_schema.py
zope/schema/tests/test_states.py
zope/schema/tests/test_vocabulary.py
zope_schema-8.0.dist-info/licenses/LICENSE.txt
zope_schema-8.0.dist-info/METADATA
zope_schema-8.0.dist-info/WHEEL
zope_schema-8.0.dist-info/top_level.txt
zope_schema-8.0.dist-info/RECORD
